foundry_wrap/__init__.py
foundry_wrap/__main__.py
foundry_wrap/cast.py
foundry_wrap/cli.py
foundry_wrap/interface_manager.py
foundry_wrap/safe.py
foundry_wrap/script_parser.py
foundry_wrap/settings.py
foundry_wrap/version.py
foundry_wrap-0.1.5.dist-info/METADATA
foundry_wrap-0.1.5.dist-info/WHEEL
foundry_wrap-0.1.5.dist-info/entry_points.txt
foundry_wrap-0.1.5.dist-info/RECORD
